commitlint/__init__.py
commitlint/__version__.py
commitlint/cli.py
commitlint/constants.py
commitlint/exceptions.py
commitlint/git_helpers.py
commitlint/messages.py
commitlint/linter/__init__.py
commitlint/linter/_linter.py
commitlint/linter/utils.py
commitlint/linter/validators.py
commitlint_autorelease-1.3.1.dist-info/LICENSE
commitlint_autorelease-1.3.1.dist-info/METADATA
commitlint_autorelease-1.3.1.dist-info/WHEEL
commitlint_autorelease-1.3.1.dist-info/entry_points.txt
commitlint_autorelease-1.3.1.dist-info/top_level.txt
commitlint_autorelease-1.3.1.dist-info/RECORD
