Metadata-Version: 2.1
Name: commitlint-autorelease
Version: 1.3.1
Summary: commitlint is is a pre-commit hook designed to lint your commit messages according to the Conventional Commits standard.
Home-page: https://github.com/opensource-nepal/commitlint
Author: opensource-nepal
Author-email: aj3sshh@gmail.com, sugatbajracharya49@gmail.com
License: GPL-3.0
Project-URL: Source, https://github.com/opensource-nepal/commitlint
Project-URL: Changelog, https://github.com/opensource-nepal/commitlint/blob/main/CHANGELOG.md
Keywords: commitlint,commit lint,python commitlint,conventional commit,conventional commit message,python commit,github actions,pre-commit
Classifier: Programming Language :: Python :: 3 :: Only
Classifier: Programming Language :: Python :: 3.8
License-File: LICENSE
